guildbotics/__init__.py
guildbotics/_version.py
guildbotics/assets/css/github-markdown-dark.css
guildbotics/assets/css/github-markdown-light.css
guildbotics/assets/css/github-markdown.css
guildbotics/cli/__init__.py
guildbotics/cli/__main__.py
guildbotics/cli/setup_tool.py
guildbotics/cli/simple/simple_brain_factory.py
guildbotics/cli/simple/simple_integration_factory.py
guildbotics/cli/simple/simple_loader_factory.py
guildbotics/cli/simple/simple_setup_tool.py
guildbotics/cli/simple/locales/cli.en.yml
guildbotics/cli/simple/locales/cli.ja.yml
guildbotics/cli/simple/templates/.env.example
guildbotics/cli/simple/templates/person.yml
guildbotics/cli/simple/templates/project.yml
guildbotics/commands/command_base.py
guildbotics/commands/discovery.py
guildbotics/commands/document_conversion_command.py
guildbotics/commands/errors.py
guildbotics/commands/markdown_command.py
guildbotics/commands/models.py
guildbotics/commands/print_command.py
guildbotics/commands/python_command.py
guildbotics/commands/registry.py
guildbotics/commands/shell_script_command.py
guildbotics/commands/spec_factory.py
guildbotics/commands/to_html_command.py
guildbotics/commands/to_pdf_command.py
guildbotics/commands/utils.py
guildbotics/commands/yaml_command.py
guildbotics/drivers/__init__.py
guildbotics/drivers/command_runner.py
guildbotics/drivers/task_scheduler.py
guildbotics/drivers/utils.py
guildbotics/entities/__init__.py
guildbotics/entities/message.py
guildbotics/entities/task.py
guildbotics/entities/team.py
guildbotics/integrations/code_hosting_service.py
guildbotics/integrations/ticket_manager.py
guildbotics/integrations/github/async_client.py
guildbotics/integrations/github/github_code_hosting_service.py
guildbotics/integrations/github/github_ticket_manager.py
guildbotics/integrations/github/github_utils.py
guildbotics/intelligences/functions.py
guildbotics/intelligences/brains/agno_agent.py
guildbotics/intelligences/brains/brain.py
guildbotics/intelligences/brains/brain_stub.py
guildbotics-0.5.5.dist-info/METADATA
guildbotics-0.5.5.dist-info/WHEEL
guildbotics-0.5.5.dist-info/entry_points.txt
guildbotics-0.5.5.dist-info/licenses/LICENSE
guildbotics-0.5.5.dist-info/licenses/third_party_licenses/github-markdown-css-license
guildbotics-0.5.5.dist-info/RECORD
