Metadata-Version: 2.4
Name: guildbotics
Version: 0.5.5
Summary: A tool to collaborate with AI agents via a task board
Project-URL: Homepage, https://github.com/GuildBotics/GuildBotics
Project-URL: Source, https://github.com/GuildBotics/GuildBotics
Project-URL: Issues, https://github.com/GuildBotics/GuildBotics/issues
Author: Ototadana
License-File: LICENSE
License-File: third_party_licenses/github-markdown-css-license
Keywords: agents,automation,multi-agent,workflow
Classifier: Environment :: Console
Classifier: Intended Audience :: Developers
Classifier: License :: OSI Approved :: MIT License
Classifier: Programming Language :: Python :: 3
Classifier: Programming Language :: Python :: 3 :: Only
Classifier: Programming Language :: Python :: 3.12
Classifier: Topic :: Utilities
Requires-Python: >=3.12
Requires-Dist: agno<2.0,>=1.7
Requires-Dist: anthropic<1.0,>=0.40
Requires-Dist: click<9.0,>=8.2
Requires-Dist: croniter>=3.0
Requires-Dist: cryptography<47,>=45
Requires-Dist: gitpython>=3.1
Requires-Dist: google-genai<2.0,>=1.29
Requires-Dist: httpx<1.0,>=0.28
Requires-Dist: jinja2>=3.1.6
Requires-Dist: langcodes>=3.3
Requires-Dist: markdown-it-py>=4.0.0
Requires-Dist: openai<2.0,>=1.106
Requires-Dist: prompt-toolkit==3.0.51
Requires-Dist: pydantic<3.0,>=2.11
Requires-Dist: pyjwt>=2.8
Requires-Dist: python-dotenv>=1.0
Requires-Dist: python-i18n>=0.3
Requires-Dist: pyyaml>=6.0
Requires-Dist: questionary>=2.1
Requires-Dist: requests>=2.32
Requires-Dist: weasyprint>=66.0
Provides-Extra: dev
Requires-Dist: black>=24.0; extra == 'dev'
Requires-Dist: types-pyyaml>=6.0; extra == 'dev'
Provides-Extra: redis
Requires-Dist: redis>=5.0; extra == 'redis'
Provides-Extra: test
Requires-Dist: pytest-asyncio>=0.23; extra == 'test'
Requires-Dist: pytest-cov>=5.0; extra == 'test'
Requires-Dist: pytest>=8.2; extra == 'test'
